n2t_hardware_tester/__init__.py
n2t_hardware_tester/main.py
n2t_hardware_tester/n2tconfig.py
n2t_hardware_tester/authutil/__init__.py
n2t_hardware_tester/authutil/auth_util.py
n2t_hardware_tester/cmdi/__init__.py
n2t_hardware_tester/cmdi/cli.py
n2t_hardware_tester/cmdi/data/h1.yml
n2t_hardware_tester/cmdi/data/h2.yml
n2t_hardware_tester/cmdi/data/h3.yml
n2t_hardware_tester/cmdi/data/h4.yml
n2t_hardware_tester/cmdi/data/h5.yml
n2t_hardware_tester/configuration/__init__.py
n2t_hardware_tester/configuration/configuration.py
n2t_hardware_tester/fetcher/__init__.py
n2t_hardware_tester/fetcher/fetcher.py
n2t_hardware_tester/grader/__init__.py
n2t_hardware_tester/grader/grader.py
n2t_hardware_tester/homeworktester/__init__.py
n2t_hardware_tester/homeworktester/homework_tester.py
n2t_hardware_tester/homeworktester/test_result.py
test/__init__.py
test/configuration/__init__.py
test/configuration/configuration_test.py
test/homeworktester/__init__.py
test/homeworktester/single_homework_test.py
n2t_hardware_tester-1.0.5.dist-info/METADATA
n2t_hardware_tester-1.0.5.dist-info/WHEEL
n2t_hardware_tester-1.0.5.dist-info/entry_points.txt
n2t_hardware_tester-1.0.5.dist-info/top_level.txt
n2t_hardware_tester-1.0.5.dist-info/RECORD
